mcp_simple_arxiv/__init__.py
mcp_simple_arxiv/__main__.py
mcp_simple_arxiv/arxiv_client.py
mcp_simple_arxiv/categories.py
mcp_simple_arxiv/server.py
mcp_simple_arxiv/taxonomy.json
mcp_simple_arxiv/update_taxonomy.py
mcp_simple_arxiv/web_server.py
mcp_simple_arxiv-0.6.0.dist-info/licenses/LICENSE
mcp_simple_arxiv-0.6.0.dist-info/METADATA
mcp_simple_arxiv-0.6.0.dist-info/WHEEL
mcp_simple_arxiv-0.6.0.dist-info/entry_points.txt
mcp_simple_arxiv-0.6.0.dist-info/top_level.txt
mcp_simple_arxiv-0.6.0.dist-info/RECORD
