Metadata-Version: 2.4
Name: mcp-simple-arxiv
Version: 0.6.0
Summary: An MCP server that provides access to arXiv papers through their API.
Author-email: Andy Brandt <andy@codesprinters.com>
License-Expression: MIT
Project-URL: Homepage, https://github.com/andybrandt/mcp-simple-arxiv
Classifier: Programming Language :: Python :: 3
Classifier: Operating System :: OS Independent
Requires-Python: >=3.10
License-File: LICENSE
Requires-Dist: fastmcp[tasks]<3.0,>=2.14
Requires-Dist: feedparser
Requires-Dist: httpx
Requires-Dist: beautifulsoup4
Requires-Dist: docling
Dynamic: license-file
